otp_cli_utils/__init__.py
otp_cli_utils/__main__.py
otp_cli_utils/constants/command_texts.py
otp_cli_utils/constants/error_texts.py
otp_cli_utils/constants/help_texts.py
otp_cli_utils/errors/invalid_input_error.py
otp_cli_utils/services/__init__.py
otp_cli_utils/services/error_handling.py
otp_cli_utils/services/img_services.py
otp_cli_utils/services/input_validation_services.py
otp_cli_utils/services/otp_services.py
otp_cli_utils/services/qr_services.py
otp_cli_utils/utils/__init__.py
otp_cli_utils/utils/msg_utils.py
otp_cli_utils-1.5.1.dist-info/licenses/LICENSE
tests/__init__.py
tests/test_get_otp_times_for_window_count.py
tests/test_get_windows_for_time_period.py
tests/test_validate_input_otp_code.py
tests/test_validate_input_secret.py
tests/test_validate_input_time_period.py
tests/test_validate_input_window_count.py
tests/test_validate_otp.py
otp_cli_utils-1.5.1.dist-info/METADATA
otp_cli_utils-1.5.1.dist-info/WHEEL
otp_cli_utils-1.5.1.dist-info/entry_points.txt
otp_cli_utils-1.5.1.dist-info/top_level.txt
otp_cli_utils-1.5.1.dist-info/RECORD
