Metadata-Version: 2.4
Name: otp-cli-utils
Version: 1.5.1
Summary: A Python CLI tool to validate OTP codes
Author: Dilanka Rathnasiri
Maintainer: Dilanka Rathnasiri
Project-URL: Homepage, https://github.com/dilanka-rathnasiri/otp-cli-utils
Project-URL: Documentation, https://github.com/dilanka-rathnasiri/otp-cli-utils
Project-URL: Source, https://github.com/dilanka-rathnasiri/otp-cli-utils
Keywords: OTP
Classifier: Programming Language :: Python :: 3.10
Classifier: Programming Language :: Python :: 3.11
Classifier: Programming Language :: Python :: 3.12
Classifier: Programming Language :: Python :: 3.13
Classifier: Operating System :: OS Independent
Requires-Python: >=3.10
License-File: LICENSE
Requires-Dist: typer
Requires-Dist: rich
Requires-Dist: pyotp
Requires-Dist: qrcode[pil]
Dynamic: license-file
